sqlalchemy_logger/__init__.py
sqlalchemy_logger/logger.py
sqlalchemy_logger-0.1.2.dist-info/METADATA
sqlalchemy_logger-0.1.2.dist-info/WHEEL
sqlalchemy_logger-0.1.2.dist-info/top_level.txt
sqlalchemy_logger-0.1.2.dist-info/RECORD
