Metadata-Version: 2.1
Name: sqlalchemy-logger
Version: 0.1.2
Summary: Logging library
Home-page: UNKNOWN
Author: Maryia Afanasyeva
Author-email: masha.afanaseva@mail.ru
License: MIT
Platform: UNKNOWN
Classifier: Intended Audience :: Developers
Classifier: License :: OSI Approved :: MIT License
Classifier: Programming Language :: Python
Classifier: Programming Language :: Python :: 3
Classifier: Programming Language :: Python :: 3.8
Classifier: Programming Language :: Python :: 3.9
Classifier: Operating System :: OS Independent
Requires-Dist: SQLAlchemy
